pytest_selenium_driver/__init__.py
pytest_selenium_driver/config.py
pytest_selenium_driver/driver_factory.py
pytest_selenium_driver/options.py
pytest_selenium_driver/parallel.py
pytest_selenium_driver/plugin.py
pytest_selenium_driver/py.typed
pytest_selenium_driver-0.1.1.dist-info/licenses/LICENSE
pytest_selenium_driver-0.1.1.dist-info/METADATA
pytest_selenium_driver-0.1.1.dist-info/WHEEL
pytest_selenium_driver-0.1.1.dist-info/entry_points.txt
pytest_selenium_driver-0.1.1.dist-info/top_level.txt
pytest_selenium_driver-0.1.1.dist-info/RECORD
