Metadata-Version: 2.4
Name: pytest-selenium-driver
Version: 0.1.1
Summary: A zero-boilerplate Selenium WebDriver fixture for pytest
Author-email: Shubham Singh <shubham.fps@gmail.com>
License: MIT
Project-URL: Homepage, https://github.com/shubhamfps/pytest-selenium-driver
Project-URL: Repository, https://github.com/shubhamfps/pytest-selenium-driver
Project-URL: Issues, https://github.com/shubhamfps/pytest-selenium-driver/issues
Project-URL: Documentation, https://github.com/shubhamfps/pytest-selenium-driver/blob/main/README.md
Project-URL: Changelog, https://github.com/shubhamfps/pytest-selenium-driver/blob/main/CHANGELOG.md
Keywords: pytest,selenium,webdriver,testing,automation,browser
Classifier: Development Status :: 4 - Beta
Classifier: Framework :: Pytest
Classifier: Intended Audience :: Developers
Classifier: License :: OSI Approved :: MIT License
Classifier: Operating System :: OS Independent
Classifier: Programming Language :: Python :: 3
Classifier: Programming Language :: Python :: 3.8
Classifier: Programming Language :: Python :: 3.9
Classifier: Programming Language :: Python :: 3.10
Classifier: Programming Language :: Python :: 3.11
Classifier: Programming Language :: Python :: 3.12
Classifier: Topic :: Software Development :: Testing
Classifier: Topic :: Software Development :: Quality Assurance
Classifier: Topic :: Internet :: WWW/HTTP :: Browsers
Requires-Python: >=3.8
License-File: LICENSE
Requires-Dist: pytest>=7.0
Requires-Dist: selenium>=4.6
Requires-Dist: hypothesis>=6.0
Provides-Extra: dev
Requires-Dist: pytest-xdist>=3.0; extra == "dev"
Requires-Dist: black>=22.0; extra == "dev"
Requires-Dist: flake8>=4.0; extra == "dev"
Requires-Dist: mypy>=0.900; extra == "dev"
Provides-Extra: test
Requires-Dist: pytest-xdist>=3.0; extra == "test"
Requires-Dist: pytest-cov>=3.0; extra == "test"
Dynamic: license-file
